forexconnect36/EachRowListener.py
forexconnect36/ForexConnect.py
forexconnect36/LiveHistory.py
forexconnect36/ResponseListener.py
forexconnect36/SessionStatusListener.py
forexconnect36/TableListener.py
forexconnect36/TableManagerListener.py
forexconnect36/__init__.py
forexconnect36/common.py
forexconnect36/errors.py
forexconnect36/lib/__init__.py
forexconnect36/lib/fxcorepy.so
forexconnect36/lib/libForexConnect.so
forexconnect36/lib/libboost_python3.so.1.64.0
forexconnect36/lib/libboost_system.so.1.64.0
forexconnect36/lib/libfxmsg.so
forexconnect36/lib/libfxtp.so
forexconnect36/lib/libgsexpat.so
forexconnect36/lib/libgstool3.so
forexconnect36/lib/libhttplib.so
forexconnect36/lib/liblog4cplus.so
forexconnect36/lib/liblogger.so
forexconnect36/lib/libpdas.so
forexconnect36/lib/libpricehistorymgr.so.2.8.0
forexconnect36/lib/libpython3.6m.so
forexconnect36/lib/libquotesmgr2.so.2.8
forexconnect36/lib/libsqlite3.8.so
forexconnect36/lib/requirements.txt
monedadigitalf36-1.6.43.post1.dist-info/METADATA
monedadigitalf36-1.6.43.post1.dist-info/WHEEL
monedadigitalf36-1.6.43.post1.dist-info/top_level.txt
monedadigitalf36-1.6.43.post1.dist-info/RECORD
