Metadata-Version: 2.1
Name: monedadigitalf36
Version: 1.6.43.post1
Summary: ForexConnect API is a trading API for the FXCM Group: https://www.fxcm.com/uk/
Home-page: https://github.com/AmadoRamos/forexconect.git
Download-URL: https://github.com/AmadoRamos/forexconect36/archive/refs/tags/v1.6.43r1.zip
Author: Gehtsoft USA, LLC
Author-email: contact@gehtsoftusa.com
License: Other/Proprietary License
Classifier: Programming Language :: Python :: 3.6
Requires-Python: >=3.6.0
